kabbes_repository_generator/CONFIG.json
kabbes_repository_generator/Client.py
kabbes_repository_generator/RepositoryGenerator.py
kabbes_repository_generator/__init__.py
kabbes_repository_generator/__main__.py
kabbes_repository_generator/Templates/default/.gitignore
kabbes_repository_generator/Templates/default/README.md
kabbes_repository_generator-0.13.0.dist-info/LICENSE
kabbes_repository_generator-0.13.0.dist-info/METADATA
kabbes_repository_generator-0.13.0.dist-info/WHEEL
kabbes_repository_generator-0.13.0.dist-info/top_level.txt
kabbes_repository_generator-0.13.0.dist-info/RECORD
