Metadata-Version: 2.1
Name: kabbes-repository-generator
Version: 0.13.0
Summary: Package for easily installing and setting up project environments
Home-page: https://pypi.org/project/kabbes-repository-generator/
Author: James Kabbes
Author-email: james.kabbes@gmail.com
Project-URL: GitHub, https://github.com/jameskabbes/repository_generator
Project-URL: Documentation, https://jameskabbes.github.io/repository_generator
Classifier: Programming Language :: Python :: 3
Classifier: License :: OSI Approved :: MIT License
Classifier: Operating System :: OS Independent
Requires-Python: >=3.7
License-File: LICENSE
Requires-Dist: GitPython
Requires-Dist: kabbes-py-starter
Requires-Dist: kabbes-parent-class
Requires-Dist: kabbes-dir-ops
Requires-Dist: kabbes-user-profile
